{
  "data": {
    "2026-01-22": [
      {
        "hour": 13,
        "timestamp": "2026-01-22T13:11:09.533321",
        "uv_index": 0.51,
        "temperature_c": -13.77,
        "humidity_pct": 77,
        "pressure_kpa": 103.7,
        "dew_point_c": -16.6,
        "wind_speed_ms": 2.91,
        "wind_direction_deg": 60,
        "clouds_pct": 100,
        "visibility_m": 628,
        "precipitation_mmh": 0.11,
        "weather_main": "Snow",
        "weather_description": "light snow",
        "is_daylight": 1
      },
      {
        "hour": 14,
        "timestamp": "2026-01-22T14:11:09.533321",
        "uv_index": 0.44,
        "temperature_c": -13.29,
        "humidity_pct": 77,
        "pressure_kpa": 103.7,
        "dew_point_c": -16.13,
        "wind_speed_ms": 3,
        "wind_direction_deg": 59,
        "clouds_pct": 100,
        "visibility_m": 560,
        "precipitation_mmh": 0.14,
        "weather_main": "Snow",
        "weather_description": "light snow",
        "is_daylight": 1
      },
      {
        "hour": 15,
        "timestamp": "2026-01-22T15:11:09.533321",
        "uv_index": 0.3,
        "temperature_c": -12.83,
        "humidity_pct": 78,
        "pressure_kpa": 103.8,
        "dew_point_c": -15.54,
        "wind_speed_ms": 3.45,
        "wind_direction_deg": 61,
        "clouds_pct": 100,
        "visibility_m": 526,
        "precipitation_mmh": 0,
        "weather_main": "Clouds",
        "weather_description": "overcast clouds",
        "is_daylight": 1
      },
      {
        "hour": 16,
        "timestamp": "2026-01-22T16:11:09.533321",
        "uv_index": 0.12,
        "temperature_c": -12.76,
        "humidity_pct": 78,
        "pressure_kpa": 103.9,
        "dew_point_c": -15.47,
        "wind_speed_ms": 3.47,
        "wind_direction_deg": 67,
        "clouds_pct": 100,
        "visibility_m": 743,
        "precipitation_mmh": 0.11,
        "weather_main": "Snow",
        "weather_description": "light snow",
        "is_daylight": 1
      },
      {
        "hour": 17,
        "timestamp": "2026-01-22T17:11:09.533321",
        "uv_index": 0,
        "temperature_c": -12.92,
        "humidity_pct": 79,
        "pressure_kpa": 104.0,
        "dew_point_c": -15.49,
        "wind_speed_ms": 3.61,
        "wind_direction_deg": 74,
        "clouds_pct": 100,
        "visibility_m": 686,
        "precipitation_mmh": 0,
        "weather_main": "Clouds",
        "weather_description": "overcast clouds",
        "is_daylight": 1
      },
      {
        "hour": 18,
        "timestamp": "2026-01-22T18:11:09.533321",
        "uv_index": 0,
        "temperature_c": -13.75,
        "humidity_pct": 80,
        "pressure_kpa": 104.2,
        "dew_point_c": -18.32,
        "wind_speed_ms": 3.89,
        "wind_direction_deg": 81,
        "clouds_pct": 100,
        "visibility_m": 728,
        "precipitation_mmh": 0,
        "weather_main": "Clouds",
        "weather_description": "overcast clouds",
        "is_daylight": 1
      },
      {
        "hour": 19,
        "timestamp": "2026-01-22T19:11:09.533321",
        "uv_index": 0,
        "temperature_c": -14.93,
        "humidity_pct": 80,
        "pressure_kpa": 104.3,
        "dew_point_c": -18.99,
        "wind_speed_ms": 3.64,
        "wind_direction_deg": 90,
        "clouds_pct": 100,
        "visibility_m": 1040,
        "precipitation_mmh": 0,
        "weather_main": "Clouds",
        "weather_description": "overcast clouds",
        "is_daylight": 1
      },
      {
        "hour": 20,
        "timestamp": "2026-01-22T20:11:09.533321",
        "uv_index": 0,
        "temperature_c": -15.21,
        "humidity_pct": 81,
        "pressure_kpa": 104.4,
        "dew_point_c": -19.27,
        "wind_speed_ms": 3.25,
        "wind_direction_deg": 96,
        "clouds_pct": 100,
        "visibility_m": 761,
        "precipitation_mmh": 0,
        "weather_main": "Clouds",
        "weather_description": "overcast clouds",
        "is_daylight": 1
      },
      {
        "hour": 21,
        "timestamp": "2026-01-22T21:11:09.533321",
        "uv_index": 0,
        "temperature_c": -15.71,
        "humidity_pct": 81,
        "pressure_kpa": 104.3,
        "dew_point_c": -19.51,
        "wind_speed_ms": 3.04,
        "wind_direction_deg": 104,
        "clouds_pct": 100,
        "visibility_m": 986,
        "precipitation_mmh": 0,
        "weather_main": "Clouds",
        "weather_description": "overcast clouds",
        "is_daylight": 1
      },
      {
        "hour": 22,
        "timestamp": "2026-01-22T22:11:09.533321",
        "uv_index": 0,
        "temperature_c": -15.61,
        "humidity_pct": 80,
        "pressure_kpa": 104.3,
        "dew_point_c": -19.78,
        "wind_speed_ms": 2.95,
        "wind_direction_deg": 110,
        "clouds_pct": 100,
        "visibility_m": 1337,
        "precipitation_mmh": 0,
        "weather_main": "Clouds",
        "weather_description": "overcast clouds",
        "is_daylight": 0
      },
      {
        "hour": 23,
        "timestamp": "2026-01-22T23:11:09.533321",
        "uv_index": 0,
        "temperature_c": -15.18,
        "humidity_pct": 80,
        "pressure_kpa": 104.3,
        "dew_point_c": -19.87,
        "wind_speed_ms": 2.97,
        "wind_direction_deg": 118,
        "clouds_pct": 100,
        "visibility_m": 1450,
        "precipitation_mmh": 0,
        "weather_main": "Clouds",
        "weather_description": "overcast clouds",
        "is_daylight": 0
      }
    ],
    "2026-01-23": [
      {
        "hour": 0,
        "timestamp": "2026-01-23T00:11:09.533321",
        "uv_index": 0,
        "temperature_c": -15.86,
        "humidity_pct": 79,
        "pressure_kpa": 104.3,
        "dew_point_c": -19.83,
        "wind_speed_ms": 2.8,
        "wind_direction_deg": 127,
        "clouds_pct": 100,
        "visibility_m": 2209,
        "precipitation_mmh": 0,
        "weather_main": "Clouds",
        "weather_description": "overcast clouds",
        "is_daylight": 0
      },
      {
        "hour": 1,
        "timestamp": "2026-01-23T01:11:09.533321",
        "uv_index": 0,
        "temperature_c": -15.77,
        "humidity_pct": 78,
        "pressure_kpa": 104.2,
        "dew_point_c": -19.74,
        "wind_speed_ms": 2.77,
        "wind_direction_deg": 134,
        "clouds_pct": 100,
        "visibility_m": 4495,
        "precipitation_mmh": 0,
        "weather_main": "Clouds",
        "weather_description": "overcast clouds",
        "is_daylight": 0
      },
      {
        "hour": 2,
        "timestamp": "2026-01-23T02:11:09.533321",
        "uv_index": 0,
        "temperature_c": -16.29,
        "humidity_pct": 77,
        "pressure_kpa": 104.2,
        "dew_point_c": -19.71,
        "wind_speed_ms": 2.5,
        "wind_direction_deg": 145,
        "clouds_pct": 100,
        "visibility_m": 10000,
        "precipitation_mmh": 0,
        "weather_main": "Clouds",
        "weather_description": "overcast clouds",
        "is_daylight": 0
      },
      {
        "hour": 3,
        "timestamp": "2026-01-23T03:11:09.533321",
        "uv_index": 0,
        "temperature_c": -17.71,
        "humidity_pct": 75,
        "pressure_kpa": 104.2,
        "dew_point_c": -19.68,
        "wind_speed_ms": 2.32,
        "wind_direction_deg": 151,
        "clouds_pct": 100,
        "visibility_m": 10000,
        "precipitation_mmh": 0,
        "weather_main": "Clouds",
        "weather_description": "overcast clouds",
        "is_daylight": 0
      },
      {
        "hour": 4,
        "timestamp": "2026-01-23T04:11:09.533321",
        "uv_index": 0,
        "temperature_c": -17.49,
        "humidity_pct": 75,
        "pressure_kpa": 104.1,
        "dew_point_c": -19.71,
        "wind_speed_ms": 2.19,
        "wind_direction_deg": 165,
        "clouds_pct": 100,
        "visibility_m": 10000,
        "precipitation_mmh": 0,
        "weather_main": "Clouds",
        "weather_description": "overcast clouds",
        "is_daylight": 0
      },
      {
        "hour": 5,
        "timestamp": "2026-01-23T05:11:09.533321",
        "uv_index": 0,
        "temperature_c": -14,
        "humidity_pct": 75,
        "pressure_kpa": 104.1,
        "dew_point_c": -19.66,
        "wind_speed_ms": 2.06,
        "wind_direction_deg": 174,
        "clouds_pct": 100,
        "visibility_m": 10000,
        "precipitation_mmh": 0,
        "weather_main": "Clouds",
        "weather_description": "overcast clouds",
        "is_daylight": 0
      },
      {
        "hour": 6,
        "timestamp": "2026-01-23T06:11:09.533321",
        "uv_index": 0,
        "temperature_c": -14.81,
        "humidity_pct": 78,
        "pressure_kpa": 104.1,
        "dew_point_c": -19.49,
        "wind_speed_ms": 1.71,
        "wind_direction_deg": 178,
        "clouds_pct": 83,
        "visibility_m": 10000,
        "precipitation_mmh": 0,
        "weather_main": "Clouds",
        "weather_description": "broken clouds",
        "is_daylight": 1
      },
      {
        "hour": 7,
        "timestamp": "2026-01-23T07:11:09.533321",
        "uv_index": 0,
        "temperature_c": -14.82,
        "humidity_pct": 79,
        "pressure_kpa": 104.1,
        "dew_point_c": -19.26,
        "wind_speed_ms": 1.64,
        "wind_direction_deg": 195,
        "clouds_pct": 52,
        "visibility_m": 10000,
        "precipitation_mmh": 0,
        "weather_main": "Clouds",
        "weather_description": "broken clouds",
        "is_daylight": 1
      },
      {
        "hour": 8,
        "timestamp": "2026-01-23T08:11:09.533321",
        "uv_index": 0,
        "temperature_c": -14.69,
        "humidity_pct": 79,
        "pressure_kpa": 104.0,
        "dew_point_c": -19.06,
        "wind_speed_ms": 1.43,
        "wind_direction_deg": 213,
        "clouds_pct": 40,
        "visibility_m": 10000,
        "precipitation_mmh": 0,
        "weather_main": "Clouds",
        "weather_description": "scattered clouds",
        "is_daylight": 1
      },
      {
        "hour": 9,
        "timestamp": "2026-01-23T09:11:09.533321",
        "uv_index": 0,
        "temperature_c": -14.21,
        "humidity_pct": 77,
        "pressure_kpa": 104.0,
        "dew_point_c": -18.83,
        "wind_speed_ms": 1.36,
        "wind_direction_deg": 234,
        "clouds_pct": 32,
        "visibility_m": 10000,
        "precipitation_mmh": 0,
        "weather_main": "Clouds",
        "weather_description": "scattered clouds",
        "is_daylight": 1
      },
      {
        "hour": 10,
        "timestamp": "2026-01-23T10:11:09.533321",
        "uv_index": 0.38,
        "temperature_c": -13.11,
        "humidity_pct": 69,
        "pressure_kpa": 103.9,
        "dew_point_c": -18.86,
        "wind_speed_ms": 1.34,
        "wind_direction_deg": 264,
        "clouds_pct": 27,
        "visibility_m": 10000,
        "precipitation_mmh": 0,
        "weather_main": "Clouds",
        "weather_description": "scattered clouds",
        "is_daylight": 1
      },
      {
        "hour": 11,
        "timestamp": "2026-01-23T11:11:09.533321",
        "uv_index": 0.67,
        "temperature_c": -12.03,
        "humidity_pct": 63,
        "pressure_kpa": 103.8,
        "dew_point_c": -18.72,
        "wind_speed_ms": 1.48,
        "wind_direction_deg": 278,
        "clouds_pct": 25,
        "visibility_m": 10000,
        "precipitation_mmh": 0,
        "weather_main": "Clouds",
        "weather_description": "scattered clouds",
        "is_daylight": 1
      },
      {
        "hour": 12,
        "timestamp": "2026-01-23T12:11:09.533321",
        "uv_index": 0.72,
        "temperature_c": -11.1,
        "humidity_pct": 58,
        "pressure_kpa": 103.7,
        "dew_point_c": -18.63,
        "wind_speed_ms": 1.36,
        "wind_direction_deg": 269,
        "clouds_pct": 86,
        "visibility_m": 10000,
        "precipitation_mmh": 0,
        "weather_main": "Clouds",
        "weather_description": "overcast clouds",
        "is_daylight": 1
      },
      {
        "hour": 13,
        "timestamp": "2026-01-23T13:11:09.533321",
        "uv_index": 0.75,
        "temperature_c": -10.37,
        "humidity_pct": 56,
        "pressure_kpa": 103.6,
        "dew_point_c": -18.52,
        "wind_speed_ms": 1.65,
        "wind_direction_deg": 238,
        "clouds_pct": 93,
        "visibility_m": 10000,
        "precipitation_mmh": 0,
        "weather_main": "Clouds",
        "weather_description": "overcast clouds",
        "is_daylight": 1
      },
      {
        "hour": 14,
        "timestamp": "2026-01-23T14:11:09.533321",
        "uv_index": 0.6,
        "temperature_c": -9.6,
        "humidity_pct": 53,
        "pressure_kpa": 103.4,
        "dew_point_c": -18.12,
        "wind_speed_ms": 1.83,
        "wind_direction_deg": 222,
        "clouds_pct": 95,
        "visibility_m": 10000,
        "precipitation_mmh": 0,
        "weather_main": "Clouds",
        "weather_description": "overcast clouds",
        "is_daylight": 1
      },
      {
        "hour": 15,
        "timestamp": "2026-01-23T15:11:09.533321",
        "uv_index": 0.34,
        "temperature_c": -8.91,
        "humidity_pct": 52,
        "pressure_kpa": 103.3,
        "dew_point_c": -17.74,
        "wind_speed_ms": 1.65,
        "wind_direction_deg": 209,
        "clouds_pct": 96,
        "visibility_m": 10000,
        "precipitation_mmh": 0,
        "weather_main": "Clouds",
        "weather_description": "overcast clouds",
        "is_daylight": 1
      },
      {
        "hour": 16,
        "timestamp": "2026-01-23T16:11:09.533321",
        "uv_index": 0.14,
        "temperature_c": -8.5,
        "humidity_pct": 52,
        "pressure_kpa": 103.2,
        "dew_point_c": -17.26,
        "wind_speed_ms": 1.36,
        "wind_direction_deg": 207,
        "clouds_pct": 97,
        "visibility_m": 10000,
        "precipitation_mmh": 0,
        "weather_main": "Clouds",
        "weather_description": "overcast clouds",
        "is_daylight": 1
      },
      {
        "hour": 17,
        "timestamp": "2026-01-23T17:11:09.533321",
        "uv_index": 0,
        "temperature_c": -8.5,
        "humidity_pct": 56,
        "pressure_kpa": 103.1,
        "dew_point_c": -16.38,
        "wind_speed_ms": 1.74,
        "wind_direction_deg": 194,
        "clouds_pct": 98,
        "visibility_m": 10000,
        "precipitation_mmh": 0,
        "weather_main": "Clouds",
        "weather_description": "overcast clouds",
        "is_daylight": 1
      },
      {
        "hour": 18,
        "timestamp": "2026-01-23T18:11:09.533321",
        "uv_index": 0,
        "temperature_c": -8.41,
        "humidity_pct": 59,
        "pressure_kpa": 103.1,
        "dew_point_c": -15.67,
        "wind_speed_ms": 1.89,
        "wind_direction_deg": 206,
        "clouds_pct": 100,
        "visibility_m": 10000,
        "precipitation_mmh": 0,
        "weather_main": "Clouds",
        "weather_description": "overcast clouds",
        "is_daylight": 1
      },
      {
        "hour": 19,
        "timestamp": "2026-01-23T19:11:09.533321",
        "uv_index": 0,
        "temperature_c": -8.06,
        "humidity_pct": 60,
        "pressure_kpa": 103.0,
        "dew_point_c": -15.09,
        "wind_speed_ms": 1.59,
        "wind_direction_deg": 211,
        "clouds_pct": 100,
        "visibility_m": 10000,
        "precipitation_mmh": 0,
        "weather_main": "Clouds",
        "weather_description": "overcast clouds",
        "is_daylight": 1
      },
      {
        "hour": 20,
        "timestamp": "2026-01-23T20:11:09.533321",
        "uv_index": 0,
        "temperature_c": -7.82,
        "humidity_pct": 60,
        "pressure_kpa": 102.9,
        "dew_point_c": -14.77,
        "wind_speed_ms": 1.13,
        "wind_direction_deg": 205,
        "clouds_pct": 100,
        "visibility_m": 10000,
        "precipitation_mmh": 0,
        "weather_main": "Clouds",
        "weather_description": "overcast clouds",
        "is_daylight": 1
      },
      {
        "hour": 21,
        "timestamp": "2026-01-23T21:11:09.533321",
        "uv_index": 0,
        "temperature_c": -7.54,
        "humidity_pct": 61,
        "pressure_kpa": 102.8,
        "dew_point_c": -14.44,
        "wind_speed_ms": 0.75,
        "wind_direction_deg": 213,
        "clouds_pct": 100,
        "visibility_m": 10000,
        "precipitation_mmh": 0,
        "weather_main": "Clouds",
        "weather_description": "overcast clouds",
        "is_daylight": 1
      },
      {
        "hour": 22,
        "timestamp": "2026-01-23T22:11:09.533321",
        "uv_index": 0,
        "temperature_c": -7.27,
        "humidity_pct": 62,
        "pressure_kpa": 102.7,
        "dew_point_c": -13.94,
        "wind_speed_ms": 0.96,
        "wind_direction_deg": 249,
        "clouds_pct": 100,
        "visibility_m": 10000,
        "precipitation_mmh": 0,
        "weather_main": "Clouds",
        "weather_description": "overcast clouds",
        "is_daylight": 0
      },
      {
        "hour": 23,
        "timestamp": "2026-01-23T23:11:09.533321",
        "uv_index": 0,
        "temperature_c": -7.02,
        "humidity_pct": 66,
        "pressure_kpa": 102.6,
        "dew_point_c": -12.96,
        "wind_speed_ms": 1.56,
        "wind_direction_deg": 294,
        "clouds_pct": 100,
        "visibility_m": 1862,
        "precipitation_mmh": 0.16,
        "weather_main": "Snow",
        "weather_description": "light snow",
        "is_daylight": 0
      }
    ],
    "2026-01-24": [
      {
        "hour": 0,
        "timestamp": "2026-01-24T00:11:09.533321",
        "uv_index": 0,
        "temperature_c": -7.11,
        "humidity_pct": 82,
        "pressure_kpa": 102.6,
        "dew_point_c": -10.26,
        "wind_speed_ms": 2.32,
        "wind_direction_deg": 286,
        "clouds_pct": 100,
        "visibility_m": 598,
        "precipitation_mmh": 0.3,
        "weather_main": "Snow",
        "weather_description": "light snow",
        "is_daylight": 0
      },
      {
        "hour": 1,
        "timestamp": "2026-01-24T01:11:09.533321",
        "uv_index": 0,
        "temperature_c": -6.57,
        "humidity_pct": 83,
        "pressure_kpa": 102.6,
        "dew_point_c": -9.62,
        "wind_speed_ms": 3.28,
        "wind_direction_deg": 296,
        "clouds_pct": 100,
        "visibility_m": 10000,
        "precipitation_mmh": 0.21,
        "weather_main": "Snow",
        "weather_description": "light snow",
        "is_daylight": 0
      },
      {
        "hour": 2,
        "timestamp": "2026-01-24T02:11:09.533321",
        "uv_index": 0,
        "temperature_c": -6.77,
        "humidity_pct": 94,
        "pressure_kpa": 102.6,
        "dew_point_c": -8.2,
        "wind_speed_ms": 4.08,
        "wind_direction_deg": 312,
        "clouds_pct": 100,
        "visibility_m": 203,
        "precipitation_mmh": 0.37,
        "weather_main": "Snow",
        "weather_description": "light snow",
        "is_daylight": 0
      },
      {
        "hour": 3,
        "timestamp": "2026-01-24T03:11:09.533321",
        "uv_index": 0,
        "temperature_c": -6.56,
        "humidity_pct": 93,
        "pressure_kpa": 102.7,
        "dew_point_c": -8.06,
        "wind_speed_ms": 4.39,
        "wind_direction_deg": 353,
        "clouds_pct": 100,
        "visibility_m": 207,
        "precipitation_mmh": 0.66,
        "weather_main": "Snow",
        "weather_description": "snow",
        "is_daylight": 0
      },
      {
        "hour": 4,
        "timestamp": "2026-01-24T04:11:09.533321",
        "uv_index": 0,
        "temperature_c": -7.98,
        "humidity_pct": 91,
        "pressure_kpa": 102.9,
        "dew_point_c": -9.81,
        "wind_speed_ms": 5.66,
        "wind_direction_deg": 2,
        "clouds_pct": 100,
        "visibility_m": 533,
        "precipitation_mmh": 0.46,
        "weather_main": "Snow",
        "weather_description": "light snow",
        "is_daylight": 0
      },
      {
        "hour": 5,
        "timestamp": "2026-01-24T05:11:09.533321",
        "uv_index": 0,
        "temperature_c": -9.18,
        "humidity_pct": 89,
        "pressure_kpa": 103.0,
        "dew_point_c": -11.45,
        "wind_speed_ms": 5.67,
        "wind_direction_deg": 0,
        "clouds_pct": 100,
        "visibility_m": 820,
        "precipitation_mmh": 0.21,
        "weather_main": "Snow",
        "weather_description": "light snow",
        "is_daylight": 0
      },
      {
        "hour": 6,
        "timestamp": "2026-01-24T06:11:09.533321",
        "uv_index": 0,
        "temperature_c": -9.92,
        "humidity_pct": 87,
        "pressure_kpa": 103.1,
        "dew_point_c": -12.58,
        "wind_speed_ms": 4.79,
        "wind_direction_deg": 356,
        "clouds_pct": 100,
        "visibility_m": 1692,
        "precipitation_mmh": 0.1,
        "weather_main": "Snow",
        "weather_description": "light snow",
        "is_daylight": 1
      },
      {
        "hour": 7,
        "timestamp": "2026-01-24T07:11:09.533321",
        "uv_index": 0,
        "temperature_c": -10.53,
        "humidity_pct": 88,
        "pressure_kpa": 103.2,
        "dew_point_c": -13.15,
        "wind_speed_ms": 4,
        "wind_direction_deg": 347,
        "clouds_pct": 100,
        "visibility_m": 937,
        "precipitation_mmh": 0,
        "weather_main": "Clouds",
        "weather_description": "overcast clouds",
        "is_daylight": 1
      },
      {
        "hour": 8,
        "timestamp": "2026-01-24T08:11:09.533321",
        "uv_index": 0,
        "temperature_c": -10.68,
        "humidity_pct": 90,
        "pressure_kpa": 103.2,
        "dew_point_c": -13.08,
        "wind_speed_ms": 3.1,
        "wind_direction_deg": 341,
        "clouds_pct": 100,
        "visibility_m": 438,
        "precipitation_mmh": 0,
        "weather_main": "Clouds",
        "weather_description": "overcast clouds",
        "is_daylight": 1
      },
      {
        "hour": 9,
        "timestamp": "2026-01-24T09:11:09.533321",
        "uv_index": 0,
        "temperature_c": -10.46,
        "humidity_pct": 89,
        "pressure_kpa": 103.2,
        "dew_point_c": -12.89,
        "wind_speed_ms": 2.48,
        "wind_direction_deg": 335,
        "clouds_pct": 100,
        "visibility_m": 342,
        "precipitation_mmh": 0,
        "weather_main": "Clouds",
        "weather_description": "overcast clouds",
        "is_daylight": 1
      },
      {
        "hour": 10,
        "timestamp": "2026-01-24T10:11:09.533321",
        "uv_index": 0.38,
        "temperature_c": -9.86,
        "humidity_pct": 86,
        "pressure_kpa": 103.2,
        "dew_point_c": -12.61,
        "wind_speed_ms": 2.64,
        "wind_direction_deg": 331,
        "clouds_pct": 100,
        "visibility_m": 452,
        "precipitation_mmh": 0.12,
        "weather_main": "Snow",
        "weather_description": "light snow",
        "is_daylight": 1
      },
      {
        "hour": 11,
        "timestamp": "2026-01-24T11:11:09.533321",
        "uv_index": 0.63,
        "temperature_c": -9.1,
        "humidity_pct": 86,
        "pressure_kpa": 103.1,
        "dew_point_c": -11.87,
        "wind_speed_ms": 3.01,
        "wind_direction_deg": 339,
        "clouds_pct": 100,
        "visibility_m": 748,
        "precipitation_mmh": 0,
        "weather_main": "Clouds",
        "weather_description": "overcast clouds",
        "is_daylight": 1
      },
      {
        "hour": 12,
        "timestamp": "2026-01-24T12:11:09.533321",
        "uv_index": 0.82,
        "temperature_c": -8.35,
        "humidity_pct": 85,
        "pressure_kpa": 103.0,
        "dew_point_c": -11.21,
        "wind_speed_ms": 2.69,
        "wind_direction_deg": 337,
        "clouds_pct": 100,
        "visibility_m": 870,
        "precipitation_mmh": 0.12,
        "weather_main": "Snow",
        "weather_description": "light snow",
        "is_daylight": 1
      }
    ]
  },
  "cached_at": "2026-01-22T13:11:10.112151",
  "lat": 51.0447,
  "lon": -114.0719,
  "date_range": "2026-01-22_2026-01-24"
}